{"cursor":"6900","size":15,"audio":[],"currentlang":"en","article":"{{Infobox scientist |name = Richard Clarke Cabot |image = Picture of Dr. R. C.\nCabot.jpg |image_size = |caption = Portrait of Dr. Richard Clarke Cabot\n|birth_date = May 21, 1868 |birth_place = Brookline, Massachusetts |death_date =\nMay 7, 1939 |death_place = |residence = |citizenship = |nationality = American\n|ethnicity = |field = |work_institutions = |alma_mater = |doctoral_advisor =\n|doctoral_students = |known_for = |influences = |influenced = |prizes =\n|religion = |footnotes = |signature = }} 'Richard Clarke Cabot' (May 21, 1868 –\nMay 7, 1939) was an American physician who advanced clinical hematology, was an\ninnovator in teaching methods, and was a pioneer in social work.\n","linknr":-1,"url":"Richard_Clarke_Cabot","recorded":1375692480,"links":[],"instances":[],"pdf":[],"categories":["1868 births","1939 deaths","People from Brookline, Massachusetts","Harvard University alumni","Social work","Guggenheim Fellows"],"headings":["Early life and education","Personal life","Professional career","References","Further reading","External links"],"image":[],"tags":[],"members":[],"related":["Brookline,_Massachusetts","United_States","Hematology","Social_work","Brookline,_Massachusetts","Ralph_Waldo_Emerson","Transcendentalism","Social_darwinism","Harvard_University","John_Dewey","Teddy_Roosevelt","Jane_Addams","Bacteriology","Massachusetts_General_Hospital","Tuberculosis","Diabetes","Social_workers","Medical_Reserve_Corps","Cabot_rings","Eponym","Murmur","Diastolic","Anemia","Heart_valve","Differential_diagnoses","Internet_Archive","JSTOR"]}